[{"id":1,"first_name":"Astrix","last_name":"Bangle","email":"abangle0@jalbum.net","country":"Albania","phone":"244-908-3129","date_of_birth":"2010-01-12T11:59:00Z"},
{"id":2,"first_name":"Brant","last_name":"Bohlens","email":"bbohlens1@guardian.co.uk","country":"China","phone":"697-189-8605","date_of_birth":"2020-11-26T05:01:31Z"},
{"id":3,"first_name":"Ardelis","last_name":"McKeowon","email":"amckeowon2@macromedia.com","country":"Cuba","phone":"146-164-8580","date_of_birth":"1967-10-22T05:50:30Z"},
{"id":4,"first_name":"Vonny","last_name":"Ovens","email":"vovens3@bloglovin.com","country":"China","phone":"782-169-7079","date_of_birth":"1986-01-28T03:37:49Z"},
{"id":5,"first_name":"Erena","last_name":"Skeels","email":"eskeels4@epa.gov","country":"Tunisia","phone":"179-954-7389","date_of_birth":"1975-12-14T05:46:05Z"},
{"id":6,"first_name":"Iolanthe","last_name":"Palk","email":"ipalk5@instagram.com","country":"Indonesia","phone":"765-446-0898","date_of_birth":"1985-08-17T01:37:02Z"},
{"id":7,"first_name":"Barrie","last_name":"Gives","email":"bgives6@prnewswire.com","country":"China","phone":"897-870-7292","date_of_birth":"1973-10-07T15:41:40Z"},
{"id":8,"first_name":"Salomone","last_name":"Brisbane","email":"sbrisbane7@i2i.jp","country":"Mongolia","phone":"819-304-5662","date_of_birth":"2000-10-12T18:22:49Z"},
{"id":9,"first_name":"Lockwood","last_name":"Springle","email":"lspringle8@mlb.com","country":"Ivory Coast","phone":"586-743-1327","date_of_birth":"1979-03-14T13:29:30Z"},
{"id":10,"first_name":"Cash","last_name":"Cumberland","email":"ccumberland9@wisc.edu","country":"China","phone":"913-665-6699","date_of_birth":"1975-03-01T15:15:05Z"},
{"id":11,"first_name":"Keri","last_name":"Laxson","email":"klaxsona@aboutads.info","country":"Indonesia","phone":"796-299-1260","date_of_birth":"1995-10-06T05:57:37Z"},
{"id":12,"first_name":"Natalee","last_name":"Gabites","email":"ngabitesb@a8.net","country":"Croatia","phone":"425-379-5673","date_of_birth":"1969-01-29T00:27:40Z"},
{"id":13,"first_name":"Moss","last_name":"Lavielle","email":"mlaviellec@hc360.com","country":"Indonesia","phone":"789-618-8503","date_of_birth":"1978-06-22T12:48:48Z"},
{"id":14,"first_name":"Alex","last_name":"Novic","email":"anovicd@hao123.com","country":"Sweden","phone":"682-879-0067","date_of_birth":"2007-02-16T00:08:37Z"},
{"id":15,"first_name":"Clevie","last_name":"Levane","email":"clevanee@naver.com","country":"Indonesia","phone":"774-444-7951","date_of_birth":"1998-05-26T15:27:06Z"},
{"id":16,"first_name":"Michel","last_name":"Dewis","email":"mdewisf@ifeng.com","country":"Indonesia","phone":"475-162-7404","date_of_birth":"2009-03-24T03:29:51Z"},
{"id":17,"first_name":"Stephanus","last_name":"Budgen","email":"sbudgeng@weibo.com","country":"Tanzania","phone":"648-519-8795","date_of_birth":"1986-08-20T06:16:32Z"},
{"id":18,"first_name":"Pacorro","last_name":"Louis","email":"plouish@youtube.com","country":"Indonesia","phone":"278-296-6880","date_of_birth":"1993-07-28T08:50:03Z"},
{"id":19,"first_name":"Channa","last_name":"Bourton","email":"cbourtoni@skype.com","country":"Sweden","phone":"747-958-0260","date_of_birth":"1979-08-11T07:47:30Z"},
{"id":20,"first_name":"Aurora","last_name":"Thal","email":"athalj@about.me","country":"Russia","phone":"674-846-1905","date_of_birth":"1969-12-07T04:58:40Z"},
{"id":21,"first_name":"Waverly","last_name":"Davenhall","email":"wdavenhallk@irs.gov","country":"Macedonia","phone":"689-191-9910","date_of_birth":"1985-05-17T02:40:09Z"},
{"id":22,"first_name":"Marena","last_name":"Stoter","email":"mstoterl@squarespace.com","country":"Ethiopia","phone":"599-212-8113","date_of_birth":"1983-10-14T14:28:07Z"},
{"id":23,"first_name":"Gawen","last_name":"Breede","email":"gbreedem@uiuc.edu","country":"France","phone":"123-670-2285","date_of_birth":"1974-10-16T22:21:42Z"},
{"id":24,"first_name":"Pamela","last_name":"Cossar","email":"pcossarn@hostgator.com","country":"Serbia","phone":"712-814-3291","date_of_birth":"2012-08-14T21:31:55Z"},
{"id":25,"first_name":"Marquita","last_name":"Reucastle","email":"mreucastleo@jigsy.com","country":"Russia","phone":"244-632-2966","date_of_birth":"2019-02-02T12:46:00Z"},
{"id":26,"first_name":"Nanette","last_name":"Hayselden","email":"nhayseldenp@wp.com","country":"Ukraine","phone":"941-593-9741","date_of_birth":"2010-01-01T14:07:22Z"},
{"id":27,"first_name":"Ingar","last_name":"MacCrosson","email":"imaccrossonq@msu.edu","country":"Indonesia","phone":"495-900-9977","date_of_birth":"2007-05-20T08:11:15Z"},
{"id":28,"first_name":"Ariana","last_name":"Kleine","email":"akleiner@latimes.com","country":"Norway","phone":"315-776-4021","date_of_birth":"1980-12-18T03:09:08Z"},
{"id":29,"first_name":"Noah","last_name":"Bradane","email":"nbradanes@china.com.cn","country":"Albania","phone":"592-752-7916","date_of_birth":"2000-12-10T21:53:28Z"},
{"id":30,"first_name":"Elka","last_name":"Featherbie","email":"efeatherbiet@ucoz.ru","country":"China","phone":"366-412-9565","date_of_birth":"1987-12-04T22:25:01Z"},
{"id":31,"first_name":"Sharia","last_name":"Leynton","email":"sleyntonu@networkadvertising.org","country":"Indonesia","phone":"347-703-7624","date_of_birth":"1996-06-08T20:29:43Z"},
{"id":32,"first_name":"Rachele","last_name":"Scrane","email":"rscranev@dailymail.co.uk","country":"France","phone":"645-626-1565","date_of_birth":"1972-06-13T15:29:12Z"},
{"id":33,"first_name":"Lynnett","last_name":"Toy","email":"ltoyw@hubpages.com","country":"China","phone":"193-470-4023","date_of_birth":"2004-08-11T19:28:33Z"},
{"id":34,"first_name":"Cullin","last_name":"Driutti","email":"cdriuttix@reference.com","country":"Japan","phone":"630-657-7727","date_of_birth":"2004-05-21T19:17:43Z"},
{"id":35,"first_name":"Auria","last_name":"Scarlon","email":"ascarlony@latimes.com","country":"Canada","phone":"880-468-1515","date_of_birth":"2011-09-23T13:05:37Z"},
{"id":36,"first_name":"Katya","last_name":"Delacourt","email":"kdelacourtz@acquirethisname.com","country":"Argentina","phone":"339-147-3074","date_of_birth":"1971-09-30T09:09:12Z"},
{"id":37,"first_name":"Shandra","last_name":"Byres","email":"sbyres10@upenn.edu","country":"Czech Republic","phone":"986-241-8442","date_of_birth":"1979-06-18T05:55:36Z"},
{"id":38,"first_name":"Maritsa","last_name":"Moralee","email":"mmoralee11@comsenz.com","country":"Tunisia","phone":"712-292-8101","date_of_birth":"2006-01-31T16:40:32Z"},
{"id":39,"first_name":"Idelle","last_name":"Beale","email":"ibeale12@illinois.edu","country":"Belarus","phone":"406-424-0837","date_of_birth":"1968-02-03T05:34:02Z"},
{"id":40,"first_name":"Isis","last_name":"Calbrathe","email":"icalbrathe13@wikispaces.com","country":"Brazil","phone":"283-116-6314","date_of_birth":"2009-02-10T11:14:37Z"},
{"id":41,"first_name":"Klara","last_name":"Vanne","email":"kvanne14@aol.com","country":"Haiti","phone":"832-337-9397","date_of_birth":"1983-11-10T00:53:44Z"},
{"id":42,"first_name":"Elsey","last_name":"Mitchelson","email":"emitchelson15@archive.org","country":"China","phone":"166-735-1890","date_of_birth":"2005-09-04T19:16:01Z"},
{"id":43,"first_name":"Parker","last_name":"Sommerscales","email":"psommerscales16@yellowbook.com","country":"Brazil","phone":"345-191-2255","date_of_birth":"2014-04-15T11:09:31Z"},
{"id":44,"first_name":"Drake","last_name":"Clitheroe","email":"dclitheroe17@berkeley.edu","country":"Norway","phone":"863-140-5258","date_of_birth":"2021-10-05T20:11:29Z"},
{"id":45,"first_name":"Jaye","last_name":"Grafton-Herbert","email":"jgraftonherbert18@ezinearticles.com","country":"Indonesia","phone":"191-534-0079","date_of_birth":"2013-12-20T07:52:08Z"},
{"id":46,"first_name":"Andy","last_name":"Mariault","email":"amariault19@java.com","country":"Indonesia","phone":"506-152-4006","date_of_birth":"2008-09-30T00:23:25Z"},
{"id":47,"first_name":"Julie","last_name":"Lippatt","email":"jlippatt1a@unc.edu","country":"France","phone":"101-331-7558","date_of_birth":"1998-02-09T12:05:09Z"},
{"id":48,"first_name":"Josias","last_name":"Brasier","email":"jbrasier1b@vistaprint.com","country":"Malawi","phone":"432-674-2961","date_of_birth":"1983-01-19T09:04:26Z"},
{"id":49,"first_name":"Kahaleel","last_name":"O'Dennehy","email":"kodennehy1c@spotify.com","country":"China","phone":"342-967-3963","date_of_birth":"2007-04-03T03:15:27Z"},
{"id":50,"first_name":"Cort","last_name":"Casacchia","email":"ccasacchia1d@ocn.ne.jp","country":"United States","phone":"918-216-6533","date_of_birth":"1967-04-15T07:15:49Z"},
{"id":51,"first_name":"Jerrome","last_name":"Bullingham","email":"jbullingham1e@umn.edu","country":"China","phone":"811-274-2401","date_of_birth":"2001-03-08T19:45:13Z"},
{"id":52,"first_name":"Joice","last_name":"Kidds","email":"jkidds1f@yahoo.com","country":"Portugal","phone":"964-224-8061","date_of_birth":"1984-07-27T05:50:48Z"},
{"id":53,"first_name":"Simonette","last_name":"Enocksson","email":"senocksson1g@livejournal.com","country":"China","phone":"388-487-8237","date_of_birth":"1966-02-08T17:40:59Z"},
{"id":54,"first_name":"Therine","last_name":"de Guise","email":"tdeguise1h@vistaprint.com","country":"Denmark","phone":"557-370-7002","date_of_birth":"2002-12-31T20:00:48Z"},
{"id":55,"first_name":"Thaine","last_name":"Kaysor","email":"tkaysor1i@goo.gl","country":"Philippines","phone":"392-815-3123","date_of_birth":"1970-12-08T20:17:01Z"},
{"id":56,"first_name":"Hymie","last_name":"Levay","email":"hlevay1j@miitbeian.gov.cn","country":"Iran","phone":"237-810-4985","date_of_birth":"2020-01-12T16:50:29Z"},
{"id":57,"first_name":"Randy","last_name":"Elrick","email":"relrick1k@ucoz.com","country":"Portugal","phone":"376-332-8901","date_of_birth":"2000-11-11T08:07:36Z"},
{"id":58,"first_name":"Krystalle","last_name":"Hotton","email":"khotton1l@blogs.com","country":"Mexico","phone":"990-130-3252","date_of_birth":"1982-10-08T20:42:08Z"},
{"id":59,"first_name":"Carolynn","last_name":"Roarty","email":"croarty1m@dell.com","country":"Yemen","phone":"303-999-2723","date_of_birth":"2011-04-20T23:00:39Z"},
{"id":60,"first_name":"Hugues","last_name":"Limpenny","email":"hlimpenny1n@ning.com","country":"Argentina","phone":"515-630-2636","date_of_birth":"2018-10-05T16:08:31Z"},
{"id":61,"first_name":"Dukie","last_name":"Frostdyke","email":"dfrostdyke1o@un.org","country":"Ukraine","phone":"911-400-7415","date_of_birth":"1990-09-30T14:21:01Z"},
{"id":62,"first_name":"Tiebout","last_name":"Scoggan","email":"tscoggan1p@nyu.edu","country":"Indonesia","phone":"804-152-3200","date_of_birth":"1989-01-27T23:06:49Z"},
{"id":63,"first_name":"Amalle","last_name":"Collingworth","email":"acollingworth1q@huffingtonpost.com","country":"Mongolia","phone":"307-484-6186","date_of_birth":"1978-06-11T07:50:16Z"},
{"id":64,"first_name":"Kearney","last_name":"Scales","email":"kscales1r@vk.com","country":"United States","phone":"718-719-2190","date_of_birth":"1979-01-16T02:57:05Z"},
{"id":65,"first_name":"Kirbie","last_name":"Redwing","email":"kredwing1s@mapquest.com","country":"Austria","phone":"708-993-9532","date_of_birth":"2012-01-13T09:48:55Z"},
{"id":66,"first_name":"Tyrone","last_name":"Stave","email":"tstave1t@naver.com","country":"Brazil","phone":"644-693-0044","date_of_birth":"1993-06-14T04:47:03Z"},
{"id":67,"first_name":"Abbie","last_name":"Gobeaux","email":"agobeaux1u@yahoo.co.jp","country":"China","phone":"973-933-3572","date_of_birth":"1969-04-03T10:02:28Z"},
{"id":68,"first_name":"Madelle","last_name":"Clink","email":"mclink1v@vkontakte.ru","country":"Indonesia","phone":"677-985-0956","date_of_birth":"1980-01-12T07:22:22Z"},
{"id":69,"first_name":"Thornie","last_name":"Tampion","email":"ttampion1w@arizona.edu","country":"Brazil","phone":"145-920-9567","date_of_birth":"1977-05-19T16:32:45Z"},
{"id":70,"first_name":"Heather","last_name":"Durtnell","email":"hdurtnell1x@wufoo.com","country":"China","phone":"254-884-2037","date_of_birth":"2002-09-01T02:58:33Z"},
{"id":71,"first_name":"Alaine","last_name":"Odom","email":"aodom1y@stanford.edu","country":"Czech Republic","phone":"807-556-9865","date_of_birth":"2004-07-18T08:44:48Z"},
{"id":72,"first_name":"Imogene","last_name":"Walworche","email":"iwalworche1z@imageshack.us","country":"Poland","phone":"203-695-7292","date_of_birth":"1997-03-24T05:32:09Z"},
{"id":73,"first_name":"Jeannine","last_name":"Simoneton","email":"jsimoneton20@de.vu","country":"China","phone":"942-128-7482","date_of_birth":"2001-09-17T12:40:34Z"},
{"id":74,"first_name":"Danni","last_name":"Woloschin","email":"dwoloschin21@virginia.edu","country":"Philippines","phone":"657-272-1166","date_of_birth":"1990-06-16T05:01:10Z"},
{"id":75,"first_name":"Kelcie","last_name":"Bulmer","email":"kbulmer22@samsung.com","country":"Costa Rica","phone":"765-872-2235","date_of_birth":"2017-03-13T01:07:39Z"},
{"id":76,"first_name":"Gustav","last_name":"Brundrett","email":"gbrundrett23@adobe.com","country":"China","phone":"114-889-5223","date_of_birth":"2014-10-15T22:59:44Z"},
{"id":77,"first_name":"Sheena","last_name":"Denson","email":"sdenson24@usatoday.com","country":"Malaysia","phone":"800-339-6816","date_of_birth":"2015-07-28T16:30:20Z"},
{"id":78,"first_name":"Dew","last_name":"Jekel","email":"djekel25@marketwatch.com","country":"Serbia","phone":"734-545-2918","date_of_birth":"2008-03-20T02:47:28Z"},
{"id":79,"first_name":"Mame","last_name":"Dunster","email":"mdunster26@harvard.edu","country":"Italy","phone":"892-113-8659","date_of_birth":"2010-10-11T11:45:50Z"},
{"id":80,"first_name":"Noby","last_name":"Burriss","email":"nburriss27@technorati.com","country":"China","phone":"665-498-5842","date_of_birth":"1972-01-17T13:36:03Z"},
{"id":81,"first_name":"Vittorio","last_name":"Feedham","email":"vfeedham28@yale.edu","country":"Malaysia","phone":"714-890-3332","date_of_birth":"2019-09-06T08:47:59Z"},
{"id":82,"first_name":"Yolanda","last_name":"Josum","email":"yjosum29@goo.ne.jp","country":"Argentina","phone":"435-188-6625","date_of_birth":"1978-02-01T03:34:54Z"},
{"id":83,"first_name":"Chuck","last_name":"McKeller","email":"cmckeller2a@slashdot.org","country":"Tunisia","phone":"588-958-6563","date_of_birth":"1966-10-26T23:05:42Z"},
{"id":84,"first_name":"Dulce","last_name":"Lundie","email":"dlundie2b@tinypic.com","country":"Indonesia","phone":"760-515-8588","date_of_birth":"1998-03-12T11:48:21Z"},
{"id":85,"first_name":"Katuscha","last_name":"Cohrs","email":"kcohrs2c@networkadvertising.org","country":"Indonesia","phone":"687-395-4494","date_of_birth":"2019-02-22T20:52:45Z"},
{"id":86,"first_name":"Putnem","last_name":"Atyea","email":"patyea2d@ow.ly","country":"Poland","phone":"335-584-3767","date_of_birth":"2014-09-28T10:45:15Z"},
{"id":87,"first_name":"Babb","last_name":"Tanslie","email":"btanslie2e@discovery.com","country":"Indonesia","phone":"210-406-3526","date_of_birth":"1986-04-30T15:58:20Z"},
{"id":88,"first_name":"Rafi","last_name":"Cogman","email":"rcogman2f@mac.com","country":"Japan","phone":"958-750-1471","date_of_birth":"1985-10-29T15:43:14Z"},
{"id":89,"first_name":"Garv","last_name":"Ledson","email":"gledson2g@hubpages.com","country":"Russia","phone":"325-409-6908","date_of_birth":"2014-08-04T06:34:19Z"},
{"id":90,"first_name":"Rhody","last_name":"Navarro","email":"rnavarro2h@t-online.de","country":"Armenia","phone":"546-229-5463","date_of_birth":"2002-11-05T14:48:00Z"},
{"id":91,"first_name":"Baudoin","last_name":"Bourne","email":"bbourne2i@harvard.edu","country":"Ecuador","phone":"757-223-7946","date_of_birth":"2015-05-06T15:12:59Z"},
{"id":92,"first_name":"Nonnah","last_name":"Rowlson","email":"nrowlson2j@squarespace.com","country":"Russia","phone":"600-480-8913","date_of_birth":"2021-08-06T19:41:01Z"},
{"id":93,"first_name":"Willa","last_name":"Bacop","email":"wbacop2k@howstuffworks.com","country":"Indonesia","phone":"993-652-0290","date_of_birth":"2003-05-24T11:36:48Z"},
{"id":94,"first_name":"Carlin","last_name":"Crew","email":"ccrew2l@ca.gov","country":"Indonesia","phone":"466-414-0693","date_of_birth":"2004-07-09T00:12:25Z"},
{"id":95,"first_name":"Babbie","last_name":"Ballchin","email":"bballchin2m@indiatimes.com","country":"United States","phone":"304-515-1861","date_of_birth":"2018-04-30T17:54:40Z"},
{"id":96,"first_name":"Kristien","last_name":"McQuaide","email":"kmcquaide2n@wikia.com","country":"Portugal","phone":"878-458-9054","date_of_birth":"2017-07-07T22:31:26Z"},
{"id":97,"first_name":"Tony","last_name":"Peltz","email":"tpeltz2o@cnbc.com","country":"Portugal","phone":"241-149-0945","date_of_birth":"2004-02-23T16:14:09Z"},
{"id":98,"first_name":"Arlin","last_name":"Halgarth","email":"ahalgarth2p@tinypic.com","country":"Thailand","phone":"224-205-3125","date_of_birth":"1999-04-14T05:15:14Z"},
{"id":99,"first_name":"Orelee","last_name":"Tatford","email":"otatford2q@redcross.org","country":"Greece","phone":"480-883-5467","date_of_birth":"1981-07-19T23:42:10Z"},
{"id":100,"first_name":"Washington","last_name":"Thorneley","email":"wthorneley2r@newsvine.com","country":"Malawi","phone":"989-540-7283","date_of_birth":"1985-05-19T06:59:25Z"},
{"id":101,"first_name":"Jamison","last_name":"Haliday","email":"jhaliday2s@sun.com","country":"Philippines","phone":"670-324-4390","date_of_birth":"1981-01-10T23:12:15Z"},
{"id":102,"first_name":"Gloriana","last_name":"Ottery","email":"gottery2t@e-recht24.de","country":"Tanzania","phone":"929-700-3284","date_of_birth":"1985-09-26T10:49:28Z"},
{"id":103,"first_name":"Tommie","last_name":"Bawle","email":"tbawle2u@freewebs.com","country":"Nigeria","phone":"703-353-7866","date_of_birth":"2010-01-20T22:27:37Z"},
{"id":104,"first_name":"Yulma","last_name":"Rankmore","email":"yrankmore2v@mapy.cz","country":"China","phone":"674-469-4452","date_of_birth":"1980-05-21T10:52:13Z"},
{"id":105,"first_name":"Stephi","last_name":"Ackenson","email":"sackenson2w@wsj.com","country":"China","phone":"748-615-0217","date_of_birth":"2006-08-10T17:57:16Z"},
{"id":106,"first_name":"Mervin","last_name":"Eaken","email":"meaken2x@springer.com","country":"Bulgaria","phone":"709-127-3778","date_of_birth":"2012-12-19T06:20:41Z"},
{"id":107,"first_name":"Leigha","last_name":"Bellino","email":"lbellino2y@globo.com","country":"France","phone":"315-793-1729","date_of_birth":"1996-10-08T04:00:32Z"},
{"id":108,"first_name":"Blondie","last_name":"Papen","email":"bpapen2z@epa.gov","country":"Yemen","phone":"567-673-6768","date_of_birth":"1981-09-24T01:13:21Z"},
{"id":109,"first_name":"Ruth","last_name":"Dunnan","email":"rdunnan30@macromedia.com","country":"Indonesia","phone":"963-782-0882","date_of_birth":"2013-05-08T14:44:49Z"},
{"id":110,"first_name":"Julienne","last_name":"Honnan","email":"jhonnan31@hhs.gov","country":"Indonesia","phone":"763-580-4906","date_of_birth":"1996-07-05T23:38:46Z"},
{"id":111,"first_name":"Collete","last_name":"Zanussii","email":"czanussii32@facebook.com","country":"Indonesia","phone":"576-101-6622","date_of_birth":"2005-02-12T11:18:27Z"},
{"id":112,"first_name":"Tandy","last_name":"Kilgrove","email":"tkilgrove33@bandcamp.com","country":"Micronesia","phone":"675-521-3065","date_of_birth":"1986-06-12T12:56:49Z"},
{"id":113,"first_name":"Merilee","last_name":"Dunrige","email":"mdunrige34@nymag.com","country":"Russia","phone":"888-800-5643","date_of_birth":"1984-07-30T07:02:51Z"},
{"id":114,"first_name":"Stillman","last_name":"Beardsall","email":"sbeardsall35@shutterfly.com","country":"Argentina","phone":"920-803-3446","date_of_birth":"2019-07-15T02:30:07Z"},
{"id":115,"first_name":"Zarah","last_name":"Olivie","email":"zolivie36@google.co.jp","country":"Indonesia","phone":"714-732-4542","date_of_birth":"1979-04-13T03:06:30Z"},
{"id":116,"first_name":"Ellie","last_name":"Gove","email":"egove37@pcworld.com","country":"Indonesia","phone":"560-258-8432","date_of_birth":"2015-08-22T12:03:10Z"},
{"id":117,"first_name":"Halsey","last_name":"Tassel","email":"htassel38@dagondesign.com","country":"Poland","phone":"636-686-6683","date_of_birth":"1989-09-25T15:50:47Z"},
{"id":118,"first_name":"Nert","last_name":"Painter","email":"npainter39@about.com","country":"Philippines","phone":"668-113-5509","date_of_birth":"1999-01-20T01:12:47Z"},
{"id":119,"first_name":"Leonid","last_name":"Ferreo","email":"lferreo3a@wordpress.com","country":"Somalia","phone":"528-948-5742","date_of_birth":"1981-07-15T06:07:00Z"},
{"id":120,"first_name":"Marchelle","last_name":"Langrick","email":"mlangrick3b@infoseek.co.jp","country":"Poland","phone":"420-839-7670","date_of_birth":"2018-03-29T03:49:19Z"},
{"id":121,"first_name":"Gordy","last_name":"Hanscomb","email":"ghanscomb3c@example.com","country":"Poland","phone":"633-731-2446","date_of_birth":"1966-11-01T15:09:39Z"},
{"id":122,"first_name":"Rhea","last_name":"Horsted","email":"rhorsted3d@weebly.com","country":"Thailand","phone":"916-968-6353","date_of_birth":"2006-07-11T19:59:42Z"},
{"id":123,"first_name":"Daisie","last_name":"Cappleman","email":"dcappleman3e@creativecommons.org","country":"China","phone":"852-457-6373","date_of_birth":"1973-08-22T17:35:43Z"},
{"id":124,"first_name":"Margie","last_name":"Bunston","email":"mbunston3f@chronoengine.com","country":"Indonesia","phone":"931-449-2535","date_of_birth":"1997-02-13T19:11:25Z"},
{"id":125,"first_name":"Kandy","last_name":"Cavee","email":"kcavee3g@clickbank.net","country":"China","phone":"766-390-3299","date_of_birth":"2006-05-13T15:07:37Z"},
{"id":126,"first_name":"Slade","last_name":"Heel","email":"sheel3h@cyberchimps.com","country":"Indonesia","phone":"850-877-0851","date_of_birth":"1979-04-08T08:06:58Z"},
{"id":127,"first_name":"Rhetta","last_name":"Laughnan","email":"rlaughnan3i@soup.io","country":"Argentina","phone":"901-461-6749","date_of_birth":"1996-12-25T05:58:29Z"},
{"id":128,"first_name":"Nikki","last_name":"Boards","email":"nboards3j@sciencedirect.com","country":"Israel","phone":"129-149-8772","date_of_birth":"1997-03-23T00:46:17Z"},
{"id":129,"first_name":"Cindie","last_name":"Hansford","email":"chansford3k@mayoclinic.com","country":"China","phone":"511-639-1569","date_of_birth":"1985-10-24T11:15:11Z"},
{"id":130,"first_name":"Odie","last_name":"Leavesley","email":"oleavesley3l@reverbnation.com","country":"Portugal","phone":"454-280-6712","date_of_birth":"1978-12-01T03:34:11Z"},
{"id":131,"first_name":"Tiffany","last_name":"Pevie","email":"tpevie3m@timesonline.co.uk","country":"Japan","phone":"480-782-1623","date_of_birth":"1998-11-07T23:12:05Z"},
{"id":132,"first_name":"Morgana","last_name":"Peplow","email":"mpeplow3n@friendfeed.com","country":"Malta","phone":"212-930-7289","date_of_birth":"1986-11-01T19:34:16Z"},
{"id":133,"first_name":"Tallie","last_name":"Dowsing","email":"tdowsing3o@youku.com","country":"Honduras","phone":"932-628-0435","date_of_birth":"2005-06-14T05:12:41Z"},
{"id":134,"first_name":"Madlen","last_name":"Mounter","email":"mmounter3p@hhs.gov","country":"Russia","phone":"968-491-9373","date_of_birth":"1983-06-04T21:14:43Z"},
{"id":135,"first_name":"Desirae","last_name":"Fessby","email":"dfessby3q@bluehost.com","country":"China","phone":"486-942-5479","date_of_birth":"2003-10-24T10:19:39Z"},
{"id":136,"first_name":"Trina","last_name":"Ferris","email":"tferris3r@wsj.com","country":"Mozambique","phone":"509-949-6784","date_of_birth":"1999-02-19T11:27:42Z"},
{"id":137,"first_name":"Maddi","last_name":"Lias","email":"mlias3s@cornell.edu","country":"Azerbaijan","phone":"985-614-6435","date_of_birth":"1974-10-26T09:20:15Z"},
{"id":138,"first_name":"Ruthie","last_name":"Tommen","email":"rtommen3t@artisteer.com","country":"China","phone":"581-154-6567","date_of_birth":"2007-02-08T23:39:45Z"},
{"id":139,"first_name":"Eduardo","last_name":"Iles","email":"eiles3u@cnbc.com","country":"Germany","phone":"868-640-5992","date_of_birth":"1988-07-18T02:58:35Z"},
{"id":140,"first_name":"Ibby","last_name":"Kilbee","email":"ikilbee3v@blinklist.com","country":"Indonesia","phone":"221-502-4582","date_of_birth":"1979-06-17T23:31:17Z"},
{"id":141,"first_name":"Gloriane","last_name":"Cammidge","email":"gcammidge3w@devhub.com","country":"Poland","phone":"894-387-3532","date_of_birth":"2017-08-10T02:51:41Z"},
{"id":142,"first_name":"Virge","last_name":"Stoppard","email":"vstoppard3x@geocities.jp","country":"Indonesia","phone":"698-114-8285","date_of_birth":"2017-11-12T08:14:14Z"},
{"id":143,"first_name":"Basia","last_name":"Lomasney","email":"blomasney3y@google.co.uk","country":"Lithuania","phone":"705-419-7321","date_of_birth":"2013-05-18T13:04:45Z"},
{"id":144,"first_name":"Evangeline","last_name":"Cockle","email":"ecockle3z@github.com","country":"France","phone":"359-529-4366","date_of_birth":"1986-08-20T08:07:16Z"},
{"id":145,"first_name":"Vinson","last_name":"Gaymer","email":"vgaymer40@eventbrite.com","country":"Indonesia","phone":"518-270-0347","date_of_birth":"1987-12-19T01:47:41Z"},
{"id":146,"first_name":"Deanna","last_name":"Baigent","email":"dbaigent41@networkadvertising.org","country":"China","phone":"870-813-7155","date_of_birth":"2006-02-13T07:35:17Z"},
{"id":147,"first_name":"Nichols","last_name":"Brolan","email":"nbrolan42@4shared.com","country":"Martinique","phone":"402-682-9257","date_of_birth":"2019-12-22T16:00:07Z"},
{"id":148,"first_name":"Irina","last_name":"Boulding","email":"iboulding43@macromedia.com","country":"Argentina","phone":"468-450-0988","date_of_birth":"2019-12-12T10:22:04Z"},
{"id":149,"first_name":"Kenna","last_name":"Gott","email":"kgott44@arstechnica.com","country":"Philippines","phone":"943-829-5356","date_of_birth":"1982-11-24T07:15:07Z"},
{"id":150,"first_name":"Kellen","last_name":"Joly","email":"kjoly45@discuz.net","country":"Czech Republic","phone":"147-957-7475","date_of_birth":"2018-03-20T21:02:16Z"},
{"id":151,"first_name":"Lola","last_name":"Cockayme","email":"lcockayme46@gizmodo.com","country":"France","phone":"770-238-8774","date_of_birth":"2017-11-28T03:41:15Z"},
{"id":152,"first_name":"Terrance","last_name":"Alves","email":"talves47@fema.gov","country":"Venezuela","phone":"262-291-6599","date_of_birth":"1994-08-30T12:06:09Z"},
{"id":153,"first_name":"Angelia","last_name":"Spurgeon","email":"aspurgeon48@answers.com","country":"China","phone":"484-878-7207","date_of_birth":"2002-08-08T14:20:19Z"},
{"id":154,"first_name":"Nedi","last_name":"Welland","email":"nwelland49@answers.com","country":"Russia","phone":"824-973-8682","date_of_birth":"2011-10-31T09:11:47Z"},
{"id":155,"first_name":"Aretha","last_name":"Scriviner","email":"ascriviner4a@seesaa.net","country":"France","phone":"878-543-5618","date_of_birth":"1977-10-18T04:27:03Z"},
{"id":156,"first_name":"Shanna","last_name":"Askell","email":"saskell4b@soup.io","country":"France","phone":"124-766-3086","date_of_birth":"2004-05-25T10:40:03Z"},
{"id":157,"first_name":"Ingaberg","last_name":"Pringer","email":"ipringer4c@goo.gl","country":"Poland","phone":"470-893-1129","date_of_birth":"1987-08-23T12:19:08Z"},
{"id":158,"first_name":"Lexine","last_name":"Terzi","email":"lterzi4d@wired.com","country":"China","phone":"423-573-6939","date_of_birth":"1996-12-28T04:42:21Z"},
{"id":159,"first_name":"Joannes","last_name":"Maxted","email":"jmaxted4e@nymag.com","country":"Norway","phone":"738-480-8608","date_of_birth":"1967-03-29T19:32:40Z"},
{"id":160,"first_name":"Idette","last_name":"Clemenzi","email":"iclemenzi4f@ameblo.jp","country":"China","phone":"866-647-9736","date_of_birth":"1978-06-04T08:24:26Z"},
{"id":161,"first_name":"Kenton","last_name":"Vellender","email":"kvellender4g@oaic.gov.au","country":"Sweden","phone":"943-199-6090","date_of_birth":"1967-06-04T12:10:32Z"},
{"id":162,"first_name":"Goldia","last_name":"Shemmans","email":"gshemmans4h@youku.com","country":"Paraguay","phone":"250-145-7070","date_of_birth":"2001-04-15T21:42:27Z"},
{"id":163,"first_name":"Kalle","last_name":"Cristoferi","email":"kcristoferi4i@virginia.edu","country":"Poland","phone":"839-107-4331","date_of_birth":"2007-10-28T19:15:59Z"},
{"id":164,"first_name":"Valaria","last_name":"Joannidi","email":"vjoannidi4j@admin.ch","country":"Russia","phone":"973-800-4364","date_of_birth":"1966-10-23T14:59:10Z"},
{"id":165,"first_name":"Sterne","last_name":"Caesmans","email":"scaesmans4k@plala.or.jp","country":"Poland","phone":"666-421-1115","date_of_birth":"2007-11-14T05:46:06Z"},
{"id":166,"first_name":"Berenice","last_name":"Sutherns","email":"bsutherns4l@wiley.com","country":"China","phone":"241-537-6786","date_of_birth":"1983-12-17T15:32:52Z"},
{"id":167,"first_name":"Harri","last_name":"Ludlom","email":"hludlom4m@csmonitor.com","country":"Sweden","phone":"703-719-5893","date_of_birth":"1979-06-24T02:38:11Z"},
{"id":168,"first_name":"Jordanna","last_name":"Morales","email":"jmorales4n@independent.co.uk","country":"Portugal","phone":"119-380-4384","date_of_birth":"2018-03-14T14:10:18Z"},
{"id":169,"first_name":"Alexandre","last_name":"Clarson","email":"aclarson4o@salon.com","country":"China","phone":"960-854-2864","date_of_birth":"2008-08-18T21:12:09Z"},
{"id":170,"first_name":"Florentia","last_name":"Eatherton","email":"featherton4p@flickr.com","country":"Russia","phone":"927-432-8508","date_of_birth":"2008-07-25T04:59:05Z"},
{"id":171,"first_name":"Karola","last_name":"Andreix","email":"kandreix4q@mediafire.com","country":"China","phone":"299-392-5764","date_of_birth":"1985-02-22T05:19:57Z"},
{"id":172,"first_name":"Malynda","last_name":"Okey","email":"mokey4r@gizmodo.com","country":"Sweden","phone":"753-986-3104","date_of_birth":"2015-11-05T00:50:24Z"},
{"id":173,"first_name":"Ravid","last_name":"Pendlington","email":"rpendlington4s@wikimedia.org","country":"Philippines","phone":"103-252-7618","date_of_birth":"2008-12-26T08:40:09Z"},
{"id":174,"first_name":"Dolli","last_name":"Kerner","email":"dkerner4t@opensource.org","country":"Japan","phone":"678-529-3905","date_of_birth":"2003-08-13T10:29:20Z"},
{"id":175,"first_name":"Perle","last_name":"Vickers","email":"pvickers4u@europa.eu","country":"United States","phone":"412-601-1356","date_of_birth":"1979-01-01T20:25:47Z"},
{"id":176,"first_name":"Clarice","last_name":"Brettor","email":"cbrettor4v@indiatimes.com","country":"Colombia","phone":"946-478-0952","date_of_birth":"2021-11-05T03:31:40Z"},
{"id":177,"first_name":"Sonnie","last_name":"Belasco","email":"sbelasco4w@cam.ac.uk","country":"Iran","phone":"333-781-4452","date_of_birth":"2004-09-04T11:40:28Z"},
{"id":178,"first_name":"Janette","last_name":"Ludwig","email":"jludwig4x@latimes.com","country":"Russia","phone":"976-891-0725","date_of_birth":"2018-07-28T16:56:23Z"},
{"id":179,"first_name":"Field","last_name":"Handrahan","email":"fhandrahan4y@chicagotribune.com","country":"China","phone":"189-575-7214","date_of_birth":"1980-08-10T06:42:34Z"},
{"id":180,"first_name":"Augie","last_name":"Toward","email":"atoward4z@google.com.hk","country":"Poland","phone":"890-414-2171","date_of_birth":"2018-05-22T13:30:26Z"},
{"id":181,"first_name":"Amberly","last_name":"Mealing","email":"amealing50@slideshare.net","country":"China","phone":"294-109-8667","date_of_birth":"1977-10-25T07:09:41Z"},
{"id":182,"first_name":"Mathian","last_name":"Eayrs","email":"meayrs51@chicagotribune.com","country":"Russia","phone":"707-800-6997","date_of_birth":"1985-12-09T06:52:18Z"},
{"id":183,"first_name":"Sascha","last_name":"Gridon","email":"sgridon52@craigslist.org","country":"Thailand","phone":"407-443-9238","date_of_birth":"2012-10-27T08:28:41Z"},
{"id":184,"first_name":"Angus","last_name":"Ortega","email":"aortega53@ucla.edu","country":"Tunisia","phone":"936-477-1594","date_of_birth":"1968-01-21T16:08:43Z"},
{"id":185,"first_name":"Margalit","last_name":"Coulman","email":"mcoulman54@sohu.com","country":"Portugal","phone":"600-875-8771","date_of_birth":"1976-08-22T05:17:06Z"},
{"id":186,"first_name":"Hephzibah","last_name":"Lamborne","email":"hlamborne55@businessweek.com","country":"Brazil","phone":"599-551-3842","date_of_birth":"1992-07-13T01:10:06Z"},
{"id":187,"first_name":"Andy","last_name":"Teodoro","email":"ateodoro56@shareasale.com","country":"Russia","phone":"843-502-9098","date_of_birth":"2008-06-30T16:54:28Z"},
{"id":188,"first_name":"Corrie","last_name":"Scala","email":"cscala57@twitpic.com","country":"Philippines","phone":"959-350-3143","date_of_birth":"2014-04-21T02:33:52Z"},
{"id":189,"first_name":"Kleon","last_name":"Dublin","email":"kdublin58@wufoo.com","country":"China","phone":"218-466-5246","date_of_birth":"1998-10-15T14:21:14Z"},
{"id":190,"first_name":"Ferdinand","last_name":"Wiseman","email":"fwiseman59@free.fr","country":"Ukraine","phone":"514-168-8519","date_of_birth":"2015-07-06T13:27:38Z"},
{"id":191,"first_name":"Rustie","last_name":"Kalvin","email":"rkalvin5a@bloglovin.com","country":"Sweden","phone":"448-158-2158","date_of_birth":"1998-12-14T18:33:48Z"},
{"id":192,"first_name":"Krystal","last_name":"Gatman","email":"kgatman5b@icq.com","country":"China","phone":"770-515-7285","date_of_birth":"1997-02-01T00:13:34Z"},
{"id":193,"first_name":"Zacharias","last_name":"Ayto","email":"zayto5c@mapy.cz","country":"China","phone":"201-774-8485","date_of_birth":"1976-01-04T11:15:02Z"},
{"id":194,"first_name":"Genni","last_name":"St Quenin","email":"gstquenin5d@sitemeter.com","country":"Indonesia","phone":"245-373-5344","date_of_birth":"1987-10-16T23:48:19Z"},
{"id":195,"first_name":"Dayna","last_name":"Neubigging","email":"dneubigging5e@ucla.edu","country":"Philippines","phone":"841-531-0323","date_of_birth":"2007-01-17T20:42:13Z"},
{"id":196,"first_name":"Tammy","last_name":"Barney","email":"tbarney5f@wix.com","country":"China","phone":"883-890-7117","date_of_birth":"2008-02-02T23:47:04Z"},
{"id":197,"first_name":"Ash","last_name":"Smitham","email":"asmitham5g@pbs.org","country":"China","phone":"691-170-6248","date_of_birth":"2010-06-06T03:26:16Z"},
{"id":198,"first_name":"Rowen","last_name":"Frushard","email":"rfrushard5h@163.com","country":"Comoros","phone":"834-938-6703","date_of_birth":"2000-05-09T20:06:57Z"},
{"id":199,"first_name":"Ashlie","last_name":"Metheringham","email":"ametheringham5i@seattletimes.com","country":"Netherlands","phone":"999-584-0317","date_of_birth":"2015-03-04T17:00:07Z"},
{"id":200,"first_name":"Leland","last_name":"Zarb","email":"lzarb5j@mysql.com","country":"China","phone":"244-763-0292","date_of_birth":"2009-01-21T04:19:23Z"}]